mici/__init__.py
mici/_version.py
mici/adapters.py
mici/errors.py
mici/integrators.py
mici/interface.py
mici/interop.py
mici/matrices.py
mici/progressbars.py
mici/samplers.py
mici/solvers.py
mici/stagers.py
mici/states.py
mici/systems.py
mici/transitions.py
mici/types.py
mici/utils.py
mici/autodiff/__init__.py
mici/autodiff/autograd_wrapper.py
mici/autodiff/jax_wrapper.py
mici/autodiff/symnum_wrapper.py
mici-0.4.1.dist-info/licenses/LICENSE
mici-0.4.1.dist-info/METADATA
mici-0.4.1.dist-info/WHEEL
mici-0.4.1.dist-info/top_level.txt
mici-0.4.1.dist-info/RECORD
