Metadata-Version: 2.4
Name: mici
Version: 0.4.1
Summary: MCMC samplers based on simulating Hamiltonian dynamics on a manifold.
Author-email: Matt Graham <m.graham@ucl.ac.uk>
Project-URL: documentation, https://matt-graham.github.io/mici
Project-URL: homepage, https://github.com/matt-graham/mici
Keywords: inference,sampling,MCMC,HMC
Classifier: Operating System :: OS Independent
Classifier: Topic :: Scientific/Engineering
Classifier: Intended Audience :: Science/Research
Classifier: Intended Audience :: Developers
Classifier: License :: OSI Approved :: MIT License
Classifier: Programming Language :: Python :: 3
Classifier: Programming Language :: Python :: 3 :: Only
Classifier: Programming Language :: Python :: 3.10
Classifier: Programming Language :: Python :: 3.11
Classifier: Programming Language :: Python :: 3.12
Classifier: Programming Language :: Python :: 3.13
Classifier: Typing :: Typed
Requires-Python: >=3.10
License-File: LICENSE
Requires-Dist: numpy>=1.22
Requires-Dist: scipy>=1.1
Provides-Extra: autograd
Requires-Dist: autograd>=1.3; extra == "autograd"
Requires-Dist: multiprocess>=0.7.0; extra == "autograd"
Provides-Extra: dev
Requires-Dist: black; extra == "dev"
Requires-Dist: build; extra == "dev"
Requires-Dist: mypy; extra == "dev"
Requires-Dist: pre-commit; extra == "dev"
Requires-Dist: pytest; extra == "dev"
Requires-Dist: ruff; extra == "dev"
Requires-Dist: tox>=4; extra == "dev"
Requires-Dist: twine; extra == "dev"
Provides-Extra: jax
Requires-Dist: jax>=0.4.1; extra == "jax"
Requires-Dist: multiprocess>=0.7.0; extra == "jax"
Provides-Extra: symnum
Requires-Dist: symnum>=0.2.1; extra == "symnum"
Dynamic: license-file
